data_trans_lib/__init__.py
data_trans_lib/transformations.py
data_trans_lib-0.1.0.dist-info/METADATA
data_trans_lib-0.1.0.dist-info/WHEEL
data_trans_lib-0.1.0.dist-info/RECORD
