Metadata-Version: 2.1
Name: data_trans_lib
Version: 0.1.0
Summary: 
Author: Indre Markeviciute
Author-email: mindre94@gmail.com
Requires-Python: >=3.9
Classifier: Programming Language :: Python :: 3
Classifier: Programming Language :: Python :: 3.9
Classifier: Programming Language :: Python :: 3.10
Classifier: Programming Language :: Python :: 3.11
Classifier: Programming Language :: Python :: 3.12
Requires-Dist: numpy (>=1.26.3,<2.0.0)
